lapa_database_helper/__init__.py
lapa_database_helper/main.py
lapa_database_helper-0.0.7.dist-info/METADATA
lapa_database_helper-0.0.7.dist-info/WHEEL
lapa_database_helper-0.0.7.dist-info/top_level.txt
lapa_database_helper-0.0.7.dist-info/RECORD
