Metadata-Version: 2.1
Name: lapa-database-helper
Version: 0.0.7
Summary: helper to access the database layer for my personal server.
Home-page: https://github.com/thepmsquare/lapa_database_helper
Author: thePmSquare
Author-email: thepmsquare@gmail.com
License: UNKNOWN
Platform: UNKNOWN
Classifier: Development Status :: 3 - Alpha
Classifier: Intended Audience :: Developers
Classifier: License :: OSI Approved :: MIT License
Classifier: Programming Language :: Python :: 3
Classifier: Programming Language :: Python :: 3.9
Requires-Dist: requests >=2.31.0
